{
    "text_boxes": [
        {
            "text": "DOLCE",
            "id": 1,
            "bbox": [
                268,
                282,
                364,
                317
            ]
        },
        {
            "text": "&",
            "id": 2,
            "bbox": [
                370,
                285,
                379,
                317
            ]
        },
        {
            "text": "GABBANA",
            "id": 3,
            "bbox": [
                387,
                285,
                540,
                323
            ]
        },
        {
            "text": "202",
            "id": 4,
            "bbox": [
                584,
                375,
                601,
                386
            ]
        },
        {
            "text": "0",
            "id": 5,
            "bbox": [
                573,
                375,
                575,
                386
            ]
        },
        {
            "text": "\u0648",
            "id": 6,
            "bbox": [
                557,
                375,
                559,
                386
            ]
        },
        {
            "text": "119",
            "id": 7,
            "bbox": [
                533,
                375,
                553,
                386
            ]
        },
        {
            "text": "\u0648",
            "id": 8,
            "bbox": [
                631,
                375,
                633,
                386
            ]
        },
        {
            "text": "12",
            "id": 9,
            "bbox": [
                614,
                375,
                622,
                386
            ]
        },
        {
            "text": "G5",
            "id": 10,
            "bbox": [
                592,
                647,
                598,
                657
            ]
        },
        {
            "text": ".",
            "id": 11,
            "bbox": [
                610,
                577,
                612,
                586
            ]
        },
        {
            "text": "\u062f\u0627",
            "id": 12,
            "bbox": [
                582,
                577,
                589,
                586
            ]
        },
        {
            "text": "\u0627\u0644\u0647",
            "id": 13,
            "bbox": [
                525,
                558,
                542,
                570
            ]
        },
        {
            "text": "ISaGiL",
            "id": 14,
            "bbox": [
                501,
                557,
                518,
                570
            ]
        },
        {
            "text": "\u0627\u0641",
            "id": 15,
            "bbox": [
                481,
                557,
                488,
                569
            ]
        },
        {
            "text": "05136501",
            "id": 16,
            "bbox": [
                261,
                555,
                320,
                569
            ]
        },
        {
            "text": "/",
            "id": 17,
            "bbox": [
                323,
                556,
                325,
                568
            ]
        },
        {
            "text": "3D",
            "id": 18,
            "bbox": [
                332,
                556,
                349,
                568
            ]
        },
        {
            "text": "401",
            "id": 19,
            "bbox": [
                366,
                556,
                382,
                568
            ]
        },
        {
            "text": "4",
            "id": 20,
            "bbox": [
                389,
                556,
                391,
                568
            ]
        },
        {
            "text": "8",
            "id": 21,
            "bbox": [
                411,
                557,
                413,
                569
            ]
        },
        {
            "text": "=",
            "id": 22,
            "bbox": [
                417,
                557,
                419,
                569
            ]
        },
        {
            "text": "10",
            "id": 23,
            "bbox": [
                427,
                557,
                431,
                569
            ]
        },
        {
            "text": "TEL",
            "id": 24,
            "bbox": [
                434,
                557,
                446,
                569
            ]
        },
        {
            "text": "\u060c",
            "id": 25,
            "bbox": [
                450,
                557,
                452,
                569
            ]
        },
        {
            "text": "ID",
            "id": 26,
            "bbox": [
                455,
                557,
                464,
                569
            ]
        },
        {
            "text": "MA",
            "id": 27,
            "bbox": [
                470,
                557,
                482,
                569
            ]
        },
        {
            "text": "n0003503",
            "id": 28,
            "bbox": [
                192,
                555,
                238,
                567
            ]
        },
        {
            "text": "2664",
            "id": 29,
            "bbox": [
                239,
                555,
                260,
                567
            ]
        },
        {
            "text": "\u0646\u0638\u0627\u0631\u062a",
            "id": 30,
            "bbox": [
                578,
                558,
                607,
                570
            ]
        },
        {
            "text": "\u0634\u0639\u0628\u0629",
            "id": 31,
            "bbox": [
                544,
                558,
                571,
                570
            ]
        }
    ],
    "fields": [
        {
            "field_name": "time",
            "key_id": [],
            "key_value": [],
            "value_text": [
                "\u0648",
                "12"
            ],
            "value_id": [
                8,
                9
            ]
        },
        {
            "field_name": "item_sku",
            "key_id": [],
            "key_value": [],
            "value_text": [
                "n0003503",
                "2664"
            ],
            "value_id": [
                28,
                29
            ]
        },
        {
            "field_name": "date",
            "key_id": [],
            "key_value": [],
            "value_text": [
                "202",
                "0",
                "\u0648",
                "119"
            ],
            "value_id": [
                4,
                5,
                6,
                7
            ]
        },
        {
            "field_name": "item_price",
            "key_id": [],
            "key_value": [],
            "value_text": [
                ".",
                "\u062f\u0627"
            ],
            "value_id": [
                11,
                12
            ]
        },
        {
            "field_name": "arabic_description",
            "key_id": [],
            "key_value": [],
            "value_text": [
                "\u0646\u0638\u0627\u0631\u062a",
                "\u0634\u0639\u0628\u0629"
            ],
            "value_id": [
                30,
                31
            ]
        },
        {
            "field_name": "item_description",
            "key_id": [],
            "key_value": [],
            "value_text": [
                "\u0627\u0644\u0647",
                "ISaGiL",
                "\u0627\u0641",
                "05136501",
                "/",
                "3D",
                "401",
                "4",
                "8",
                "=",
                "10",
                "TEL",
                "\u060c",
                "ID",
                "MA"
            ],
            "value_id": [
                13,
                14,
                15,
                16,
                17,
                18,
                19,
                20,
                21,
                22,
                23,
                24,
                25,
                26,
                27
            ]
        },
        {
            "field_name": "store_name",
            "key_id": [],
            "key_value": [],
            "value_text": [
                "DOLCE",
                "&",
                "GABBANA"
            ],
            "value_id": [
                1,
                2,
                3
            ]
        },
        {
            "field_name": "total",
            "key_id": [],
            "key_value": [],
            "value_text": [
                "G5"
            ],
            "value_id": [
                10
            ]
        }
    ],
    "global_attributes": {
        "file_id": "./data/images/1242.jpg"
    }
}