{
    "text_boxes": [
        {
            "text": "2020",
            "id": 1,
            "bbox": [
                448,
                225,
                474,
                240
            ]
        },
        {
            "text": ",",
            "id": 2,
            "bbox": [
                440,
                227,
                444,
                240
            ]
        },
        {
            "text": "yll",
            "id": 3,
            "bbox": [
                413,
                226,
                440,
                241
            ]
        },
        {
            "text": "\u0627\u0644",
            "id": 4,
            "bbox": [
                397,
                227,
                419,
                241
            ]
        },
        {
            "text": "23:42",
            "id": 5,
            "bbox": [
                484,
                224,
                516,
                238
            ]
        },
        {
            "text": "3,790.00",
            "id": 6,
            "bbox": [
                549,
                560,
                607,
                575
            ]
        },
        {
            "text": "3790.00",
            "id": 7,
            "bbox": [
                620,
                390,
                671,
                405
            ]
        },
        {
            "text": "1",
            "id": 8,
            "bbox": [
                373,
                403,
                376,
                412
            ]
        },
        {
            "text": "1",
            "id": 9,
            "bbox": [
                374,
                441,
                378,
                452
            ]
        },
        {
            "text": "O",
            "id": 10,
            "bbox": [
                77,
                391,
                82,
                405
            ]
        },
        {
            "text": "-",
            "id": 11,
            "bbox": [
                91,
                392,
                93,
                406
            ]
        },
        {
            "text": "CASE",
            "id": 12,
            "bbox": [
                94,
                392,
                128,
                410
            ]
        },
        {
            "text": "A32725802395C229",
            "id": 13,
            "bbox": [
                76,
                409,
                208,
                430
            ]
        }
    ],
    "fields": [
        {
            "field_name": "time",
            "key_id": [],
            "key_value": [],
            "value_text": [
                "23:42"
            ],
            "value_id": [
                5
            ]
        },
        {
            "field_name": "item_sku",
            "key_id": [],
            "key_value": [],
            "value_text": [
                "A32725802395C229"
            ],
            "value_id": [
                13
            ]
        },
        {
            "field_name": "date",
            "key_id": [],
            "key_value": [],
            "value_text": [
                "2020",
                ",",
                "yll",
                "\u0627\u0644"
            ],
            "value_id": [
                1,
                2,
                3,
                4
            ]
        },
        {
            "field_name": "item_price",
            "key_id": [],
            "key_value": [],
            "value_text": [
                "3790.00"
            ],
            "value_id": [
                7
            ]
        },
        {
            "field_name": "item_description",
            "key_id": [],
            "key_value": [],
            "value_text": [
                "O",
                "-",
                "CASE"
            ],
            "value_id": [
                10,
                11,
                12
            ]
        },
        {
            "field_name": "total_items",
            "key_id": [],
            "key_value": [],
            "value_text": [
                "1"
            ],
            "value_id": [
                9
            ]
        },
        {
            "field_name": "item_quantity",
            "key_id": [],
            "key_value": [],
            "value_text": [
                "1"
            ],
            "value_id": [
                8
            ]
        },
        {
            "field_name": "total",
            "key_id": [],
            "key_value": [],
            "value_text": [
                "3,790.00"
            ],
            "value_id": [
                6
            ]
        }
    ],
    "global_attributes": {
        "file_id": "./data/images/127.jpg"
    }
}