{
    "text_boxes": [
        {
            "text": "ITEM",
            "id": 1,
            "bbox": [
                632,
                1360,
                686,
                1385
            ]
        },
        {
            "text": "U.",
            "id": 2,
            "bbox": [
                648,
                1294,
                697,
                1330
            ]
        },
        {
            "text": "PRICE",
            "id": 3,
            "bbox": [
                579,
                1300,
                647,
                1323
            ]
        },
        {
            "text": "QTY",
            "id": 4,
            "bbox": [
                494,
                1300,
                534,
                1321
            ]
        },
        {
            "text": "(-REBATE)",
            "id": 5,
            "bbox": [
                356,
                1296,
                475,
                1322
            ]
        },
        {
            "text": "TOTAL",
            "id": 6,
            "bbox": [
                214,
                1297,
                282,
                1321
            ]
        },
        {
            "text": "PRICE",
            "id": 7,
            "bbox": [
                130,
                1298,
                199,
                1321
            ]
        },
        {
            "text": "\u0645\u062c\u0645\u0648\u0639",
            "id": 8,
            "bbox": [
                126,
                1260,
                194,
                1279
            ]
        },
        {
            "text": "\u0641\u0631",
            "id": 9,
            "bbox": [
                210,
                1264,
                233,
                1284
            ]
        },
        {
            "text": "\u0639\u064a",
            "id": 10,
            "bbox": [
                239,
                1263,
                265,
                1280
            ]
        },
        {
            "text": "029714582520",
            "id": 11,
            "bbox": [
                523,
                1194,
                690,
                1218
            ]
        },
        {
            "text": "(6)",
            "id": 12,
            "bbox": [
                469,
                1193,
                504,
                1219
            ]
        },
        {
            "text": "STUDIOSKINFULLCOVERAGE",
            "id": 13,
            "bbox": [
                141,
                1195,
                451,
                1219
            ]
        },
        {
            "text": "24",
            "id": 14,
            "bbox": [
                97,
                1195,
                124,
                1217
            ]
        },
        {
            "text": "HRFOU",
            "id": 15,
            "bbox": [
                622,
                1160,
                690,
                1184
            ]
        },
        {
            "text": "180.00",
            "id": 16,
            "bbox": [
                94,
                1091,
                176,
                1117
            ]
        },
        {
            "text": "180.00",
            "id": 17,
            "bbox": [
                549,
                1090,
                628,
                1116
            ]
        },
        {
            "text": "*",
            "id": 18,
            "bbox": [
                521,
                1094,
                534,
                1113
            ]
        },
        {
            "text": "1",
            "id": 19,
            "bbox": [
                496,
                1090,
                502,
                1114
            ]
        },
        {
            "text": "072713616329",
            "id": 20,
            "bbox": [
                521,
                1056,
                688,
                1081
            ]
        },
        {
            "text": "(6)",
            "id": 21,
            "bbox": [
                468,
                1054,
                504,
                1081
            ]
        },
        {
            "text": "HB",
            "id": 22,
            "bbox": [
                422,
                1057,
                449,
                1081
            ]
        },
        {
            "text": "DESERT",
            "id": 23,
            "bbox": [
                324,
                1057,
                407,
                1081
            ]
        },
        {
            "text": "DUSK",
            "id": 24,
            "bbox": [
                252,
                1057,
                307,
                1081
            ]
        },
        {
            "text": "E/SHAD",
            "id": 25,
            "bbox": [
                151,
                1054,
                234,
                1082
            ]
        },
        {
            "text": "PAL",
            "id": 26,
            "bbox": [
                93,
                1058,
                134,
                1081
            ]
        },
        {
            "text": "ETTE",
            "id": 27,
            "bbox": [
                635,
                1020,
                689,
                1047
            ]
        },
        {
            "text": "263.00",
            "id": 28,
            "bbox": [
                89,
                951,
                175,
                983
            ]
        },
        {
            "text": "263.00",
            "id": 29,
            "bbox": [
                552,
                952,
                636,
                978
            ]
        },
        {
            "text": "*",
            "id": 30,
            "bbox": [
                524,
                957,
                536,
                975
            ]
        },
        {
            "text": "1",
            "id": 31,
            "bbox": [
                498,
                952,
                504,
                977
            ]
        }
    ],
    "fields": [
        {
            "field_name": "lineItems",
            "key_id": [],
            "key_value": [],
            "value_text": [
                "029714582520",
                "(6)",
                "STUDIOSKINFULLCOVERAGE",
                "24",
                "HRFOU",
                "180.00",
                "180.00",
                "*",
                "1",
                "072713616329",
                "(6)",
                "HB",
                "DESERT",
                "DUSK",
                "E/SHAD",
                "PAL",
                "ETTE",
                "263.00",
                "263.00",
                "*",
                "1"
            ],
            "value_id": [
                11,
                12,
                13,
                14,
                15,
                16,
                17,
                18,
                19,
                20,
                21,
                22,
                23,
                24,
                25,
                26,
                27,
                28,
                29,
                30,
                31
            ]
        },
        {
            "field_name": "heading",
            "key_id": [],
            "key_value": [],
            "value_text": [
                "ITEM",
                "U.",
                "PRICE",
                "QTY",
                "(-REBATE)",
                "TOTAL",
                "PRICE",
                "\u0645\u062c\u0645\u0648\u0639",
                "\u0641\u0631",
                "\u0639\u064a"
            ],
            "value_id": [
                1,
                2,
                3,
                4,
                5,
                6,
                7,
                8,
                9,
                10
            ]
        }
    ],
    "global_attributes": {
        "file_id": "./data/images/160.jpg"
    }
}