{
    "text_boxes": [
        {
            "text": "Cafe",
            "id": 1,
            "bbox": [
                154,
                606,
                187,
                622
            ]
        },
        {
            "text": "Latte",
            "id": 2,
            "bbox": [
                197,
                608,
                238,
                622
            ]
        },
        {
            "text": "37.00",
            "id": 3,
            "bbox": [
                428,
                609,
                470,
                625
            ]
        },
        {
            "text": "A",
            "id": 4,
            "bbox": [
                489,
                612,
                496,
                624
            ]
        },
        {
            "text": "Latte",
            "id": 5,
            "bbox": [
                195,
                647,
                236,
                663
            ]
        },
        {
            "text": "37.00",
            "id": 6,
            "bbox": [
                427,
                651,
                469,
                666
            ]
        },
        {
            "text": "A",
            "id": 7,
            "bbox": [
                489,
                653,
                496,
                666
            ]
        },
        {
            "text": "49.00",
            "id": 8,
            "bbox": [
                427,
                672,
                469,
                687
            ]
        },
        {
            "text": "A",
            "id": 9,
            "bbox": [
                489,
                673,
                496,
                687
            ]
        },
        {
            "text": "Trocadero",
            "id": 10,
            "bbox": [
                146,
                707,
                225,
                726
            ]
        },
        {
            "text": "49.00",
            "id": 11,
            "bbox": [
                426,
                713,
                469,
                732
            ]
        },
        {
            "text": "A",
            "id": 12,
            "bbox": [
                488,
                716,
                496,
                731
            ]
        },
        {
            "text": "Description",
            "id": 13,
            "bbox": [
                161,
                551,
                250,
                566
            ]
        },
        {
            "text": "Amount",
            "id": 14,
            "bbox": [
                420,
                552,
                468,
                565
            ]
        }
    ],
    "fields": [
        {
            "field_name": "lineItems",
            "key_id": [],
            "key_value": [],
            "value_text": [
                "Cafe",
                "Latte",
                "37.00",
                "A",
                "Latte",
                "37.00",
                "A",
                "49.00",
                "A",
                "Trocadero",
                "49.00",
                "A"
            ],
            "value_id": [
                1,
                2,
                3,
                4,
                5,
                6,
                7,
                8,
                9,
                10,
                11,
                12
            ]
        },
        {
            "field_name": "heading",
            "key_id": [],
            "key_value": [],
            "value_text": [
                "Description",
                "Amount"
            ],
            "value_id": [
                13,
                14
            ]
        }
    ],
    "global_attributes": {
        "file_id": "./data/images/625.jpg"
    }
}